geet/__init__.py
geet/__main__.py
geet/about.py
geet/constants.py
geet/core.py
geet/default_apps_list_data.json
geet/default_shared_data.json
geet/handlers.py
geet/lib/__init__.py
geet/lib/gurl.py
geet/lib/jasonix.py
geet/pyrustic_data/about.json
tests/__init__.py
geet-0.0.3.dist-info/LICENSE
geet-0.0.3.dist-info/METADATA
geet-0.0.3.dist-info/WHEEL
geet-0.0.3.dist-info/top_level.txt
geet-0.0.3.dist-info/RECORD
