Metadata-Version: 2.1
Name: geet
Version: 0.0.3
Summary: Get, install, and run the latest release of a compatible app published on Github
Home-page: https://github.com/pyrustic/geet
Author: Pyrustic Evangelist
Author-email: pyrustic@protonmail.com
License: UNKNOWN
Platform: UNKNOWN
Classifier: Programming Language :: Python :: 3
Classifier: License :: OSI Approved :: MIT License
Classifier: Operating System :: OS Independent
Requires-Python: >=3.5
